CHANGELOG.txt
LICENSE.txt
MANIFEST.in
README.txt
setup.py
MiloScraper/__init__.py
MiloScraper.egg-info/PKG-INFO
MiloScraper.egg-info/SOURCES.txt
MiloScraper.egg-info/dependency_links.txt
MiloScraper.egg-info/requires.txt
MiloScraper.egg-info/top_level.txt