Metadata-Version: 2.1
Name: MiloScraper
Version: 0.0.4
Summary: an project that works like requests but also works on replit
Home-page: 
Author: Culty
Author-email: sleepyculty@gmail.com
License: MIT
Keywords: scraper
Classifier: Development Status :: 5 - Production/Stable
Classifier: Intended Audience :: Education
Classifier: Operating System :: Microsoft :: Windows :: Windows 10
Classifier: License :: OSI Approved :: MIT License
Classifier: Programming Language :: Python :: 3
License-File: LICENSE.txt
